pi_conf/__init__.py
pi_conf/attr_dict.py
pi_conf/config.py
pi_conf/config_settings.py
pi_conf/definitions.py
pi_conf/module_check.py
pi_conf/open_func.py
pi_conf/provenance.py
pi_conf/py.typed
pi_conf-0.8.5.2.dist-info/LICENSE
pi_conf-0.8.5.2.dist-info/METADATA
pi_conf-0.8.5.2.dist-info/WHEEL
pi_conf-0.8.5.2.dist-info/RECORD
