Metadata-Version: 2.1
Name: pi-conf
Version: 0.8.5.2
Summary: Easy configs for python projects
License: MIT
Author: parnell
Author-email: 3028114+parnell@users.noreply.github.com
Requires-Python: >=3.9,<4.0
Classifier: License :: OSI Approved :: MIT License
Classifier: Programming Language :: Python :: 3
Classifier: Programming Language :: Python :: 3.9
Classifier: Programming Language :: Python :: 3.10
Classifier: Programming Language :: Python :: 3.11
Classifier: Programming Language :: Python :: 3.12
Provides-Extra: yaml
Requires-Dist: platformdirs (>=3.0.0)
Requires-Dist: toml (>=0.10.2,<0.11.0) ; python_full_version > "3.0.0" and python_version < "3.11"
